.DS_Store
iron_datastructures/__init__.py
iron_datastructures/_queue_position.py
iron_datastructures/_queue_position.pyi
iron_datastructures/circular_queue.py
iron_datastructures/circular_queue.pyi
iron_datastructures/graph.py
iron_datastructures/graph.pyi
iron_datastructures/graph_node.py
iron_datastructures/graph_node.pyi
iron_datastructures/linked_list.py
iron_datastructures/linked_list.pyi
iron_datastructures/linked_list_node.py
iron_datastructures/linked_list_node.pyi
iron_datastructures/py.typed
iron_datastructures/stack.py
iron_datastructures/stack.pyi
iron_datastructures-1.4.dist-info/LICENSE
iron_datastructures-1.4.dist-info/METADATA
iron_datastructures-1.4.dist-info/WHEEL
iron_datastructures-1.4.dist-info/top_level.txt
iron_datastructures-1.4.dist-info/RECORD
