Metadata-Version: 2.1
Name: iron-datastructures
Version: 1.4
Summary: A set of useful data structures, including circular queue, binary tree/graph, linked list, and stack.
Home-page: https://github.com/ntflix/iron_datastructures
Author: Felix Weber
Author-email: felix@iron59.co.uk
License: GNU GPLv3
Platform: UNKNOWN
